tkfly/__init__.py
tkfly/__main__.py
tkfly/_blend2d/darwin-x64/libblend2d.dylib
tkfly/_blend2d/darwin-x64/libtclb2d.dylib
tkfly/_blend2d/darwin-x64/libtkb2d.dylib
tkfly/_blend2d/demo/Blacksword.otf
tkfly/_blend2d/demo/comp-op/chessboard.png
tkfly/_blend2d/demo/comp-op/CMYK.png
tkfly/_blend2d/demo/comp-op/CompositionTest.tcl
tkfly/_blend2d/demo/comp-op/PorterDuffInAction.tcl
tkfly/_blend2d/demo/comp-op/RGB.png
tkfly/_blend2d/demo/demo-tiger/demo-tiger.tcl
tkfly/_blend2d/demo/demo-tiger/develTools/bl-qt-tiger.h
tkfly/_blend2d/demo/demo-tiger/develTools/Ghostscript_Tiger.svg
tkfly/_blend2d/demo/demo-tiger/develTools/tiger-conversion.cpp
tkfly/_blend2d/demo/demo-tiger/develTools/tiger-conversion.exe
tkfly/_blend2d/demo/demo-tiger/tiger-data.tcl
tkfly/_blend2d/demo/greenSlate.jpg
tkfly/_blend2d/demo/lib/EbuttonColor-1.0.1.tm
tkfly/_blend2d/demo/lib/Eseparator-1.0.tm
tkfly/_blend2d/demo/lib/hatching-1.0.tm
tkfly/_blend2d/demo/lib/IKscale-1.0.1.tm
tkfly/_blend2d/demo/lib/perlin-1.0/darwin-x64/perlin.dylib
tkfly/_blend2d/demo/lib/perlin-1.0/license.terms
tkfly/_blend2d/demo/lib/perlin-1.0/linux-x32/perlin.so
tkfly/_blend2d/demo/lib/perlin-1.0/linux-x64/perlin.so
tkfly/_blend2d/demo/lib/perlin-1.0/pkgIndex.tcl
tkfly/_blend2d/demo/lib/perlin-1.0/win-x32/perlin.dll
tkfly/_blend2d/demo/lib/perlin-1.0/win-x64/perlin.dll
tkfly/_blend2d/demo/lib/sketchline-1.0.tm
tkfly/_blend2d/demo/lib/snit.2.3.2/main2.tcl
tkfly/_blend2d/demo/lib/snit.2.3.2/pkgIndex.tcl
tkfly/_blend2d/demo/lib/snit.2.3.2/snit2.tcl
tkfly/_blend2d/demo/lib/snit.2.3.2/teapot.txt
tkfly/_blend2d/demo/lib/snit.2.3.2/validate.tcl
tkfly/_blend2d/demo/lib/Spline-1.0.tm
tkfly/_blend2d/demo/moby.svg
tkfly/_blend2d/demo/Q/layer_1.svg
tkfly/_blend2d/demo/Q/layer_2.svg
tkfly/_blend2d/demo/Q/layer_3.svg
tkfly/_blend2d/demo/Q/layer_4.svg
tkfly/_blend2d/demo/Q/layer_5.svg
tkfly/_blend2d/demo/Q/layer_6.svg
tkfly/_blend2d/demo/Road_Rage-License.txt
tkfly/_blend2d/demo/Road_Rage.otf
tkfly/_blend2d/demo/sample-poly.tcl
tkfly-0.1.0.dist-info/METADATA
tkfly-0.1.0.dist-info/WHEEL
tkfly-0.1.0.dist-info/RECORD
